setup.py
ambari_client/__init__.py
ambari_client/ambari_api.py
ambari_client.egg-info/PKG-INFO
ambari_client.egg-info/SOURCES.txt
ambari_client.egg-info/dependency_links.txt
ambari_client.egg-info/requires.txt
ambari_client.egg-info/top_level.txt