Metadata-Version: 1.0
Name: ambari-client
Version: 1.0.3-SNAPSHOT
Summary: Ambari python REST API client
Home-page: UNKNOWN
Author: UNKNOWN
Author-email: ambari-dev@incubator.apache.org
License: Apache License 2.0
Platform: UNKNOWN
